raitracker/README.md
raitracker/__init__.py
raitracker/_version.py
raitracker/handlers.py
raitracker/labextension/package.json
raitracker/labextension/static/256.cc959255c5755946a761.js
raitracker/labextension/static/456.d8dfe1de957a8d107948.js
raitracker/labextension/static/480.965c9d09f8a7bf72a667.js
raitracker/labextension/static/480.965c9d09f8a7bf72a667.js.LICENSE.txt
raitracker/labextension/static/486.39e058ed610d14fda98d.js
raitracker/labextension/static/486.39e058ed610d14fda98d.js.LICENSE.txt
raitracker/labextension/static/50.354fe5ceb6b5e767956c.js
raitracker/labextension/static/549.c1ad8c96dd0747bccee1.js
raitracker/labextension/static/687.ee5de0cadc611673949c.js
raitracker/labextension/static/838.b906318cb72b276de8bb.js
raitracker/labextension/static/remoteEntry.71218c044e7cefb5547c.js
raitracker/labextension/static/style.js
raitracker/labextension/static/third-party-licenses.json
raitracker/src/__init__.py
raitracker/src/registration.py
raitracker/src/core/__init__.py
raitracker/src/core/component_types.py
raitracker/src/core/utils.py
raitracker/src/dataset/__init__.py
raitracker/src/dataset/load_data.py
raitracker/src/metrics/__init__.py
raitracker/src/metrics/classification.py
raitracker/src/metrics/general.py
raitracker/src/metrics/regression.py
raitracker/src/metrics/utils.py
raitracker/src/platforms/__init__.py
raitracker/src/platforms/constants.py
raitracker/src/platforms/keras.py
raitracker/src/platforms/pytorch.py
raitracker/src/platforms/sklearn.py
raitracker/test/__init__.py
raitracker/test/conftest.py
raitracker/test/constants.py
raitracker/test/test_register.py
raitracker/training/src/convert_datasets_to_txt.py
raitracker/training/src/generate_models.sh
raitracker/training/src/save_model_tf.py
raitracker/training/src/save_model_torch.py
raitracker/training/src/save_model_torch_light.py
raitracker/training/src/toy_dataset.py
raitracker/training/src/train_sklearn_estimator.py
raitracker/training/src/model/__init__.py
raitracker-0.2.0.dist-info/METADATA
raitracker-0.2.0.dist-info/WHEEL
raitracker-0.2.0.dist-info/licenses/LICENSE.md
raitracker-0.2.0.dist-info/RECORD
