Metadata-Version: 2.1
Name: raitracker
Version: 0.2.0
Summary: Responsible AI Toolbox Tracker
Project-URL: Homepage, https://github.com/microsoft/responsible-ai-toolbox-tracker
Project-URL: Bug Tracker, https://github.com/microsoft/responsible-ai-toolbox-tracker/issues
Project-URL: Repository, https://github.com/microsoft/responsible-ai-toolbox-tracker.git
Author-email: "Besmira Nushi, Rahee Ghosh Peshawaria, Jingya Chen, ThuVan Pham, Marah Abdin, Irina Spiridonova, Ece Kamar, Matheus Mendonca, Mark Encarnacion, Dany Rouhana" <rai-toolbox@microsoft.com>
License: MIT License
License-File: LICENSE.md
Classifier: Framework :: Jupyter
Classifier: Framework :: Jupyter :: JupyterLab
Classifier: Framework :: Jupyter :: JupyterLab :: 3
Classifier: Framework :: Jupyter :: JupyterLab :: Extensions
Classifier: Framework :: Jupyter :: JupyterLab :: Extensions :: Prebuilt
Classifier: License :: OSI Approved :: BSD License
Classifier: Programming Language :: Python
Classifier: Programming Language :: Python :: 3
Classifier: Programming Language :: Python :: 3.7
Classifier: Programming Language :: Python :: 3.8
Classifier: Programming Language :: Python :: 3.9
Classifier: Programming Language :: Python :: 3.10
Requires-Python: >=3.7
Requires-Dist: jupyterlab>=3
Requires-Dist: mlflow>=2
Requires-Dist: numpy>=1
Requires-Dist: pandas>=1
Requires-Dist: scikit-learn>=1
Provides-Extra: all
Requires-Dist: pytorch-lightning==1.7; extra == 'all'
Requires-Dist: tensorflow; extra == 'all'
Requires-Dist: torch; extra == 'all'
Requires-Dist: torchmetrics==0.7; extra == 'all'
Provides-Extra: dev
Requires-Dist: lightgbm; extra == 'dev'
Requires-Dist: matplotlib; extra == 'dev'
Requires-Dist: nbsphinx; extra == 'dev'
Requires-Dist: pytest; extra == 'dev'
Requires-Dist: pytest-cov; extra == 'dev'
Requires-Dist: pytorch-lightning==1.7; extra == 'dev'
Requires-Dist: sphinx; extra == 'dev'
Requires-Dist: sphinx-rtd-theme>=1.1.1; extra == 'dev'
Requires-Dist: tensorflow; extra == 'dev'
Requires-Dist: torch; extra == 'dev'
Requires-Dist: torchmetrics==0.7; extra == 'dev'
Requires-Dist: xgboost; extra == 'dev'
